README.md
setup.py
amqp_client/__init__.py
amqp_client/amqp.py
amqp_client/fake.py
pulsar_amqp.egg-info/PKG-INFO
pulsar_amqp.egg-info/SOURCES.txt
pulsar_amqp.egg-info/dependency_links.txt
pulsar_amqp.egg-info/top_level.txt