Metadata-Version: 1.1
Name: pulsar-amqp
Version: 0.2.2
Summary: Pulsar wrapper for aioamqp
Home-page: https://github.com/scailer/pulsar-aioamqp
Author: Dmitriy Vlasov
Author-email: scailer@yandex.ru
License: MIT license
Platform: UNKNOWN
Classifier: Development Status :: 4 - Beta
Classifier: Environment :: Plugins
Classifier: Intended Audience :: Developers
Classifier: License :: OSI Approved :: MIT License
Classifier: Programming Language :: Python
Classifier: Programming Language :: Python :: 3
Classifier: Programming Language :: Python :: 3.5
Classifier: Topic :: Software Development :: Libraries :: Python Modules
Requires: aioamqp
Requires: pulsar (>= 1.5.4)
